geomapper/__init__.py
geomapper/geomapper.py
geomapper-0.0.2.dist-info/LICENSE
geomapper-0.0.2.dist-info/METADATA
geomapper-0.0.2.dist-info/WHEEL
geomapper-0.0.2.dist-info/top_level.txt
geomapper-0.0.2.dist-info/RECORD
